docuwarp/__init__.py
docuwarp/cli.py
docuwarp/unwarp.py
docuwarp/artifacts/bilinear_unwarping.onnx
docuwarp/artifacts/uvdoc.onnx
docuwarp-1.0.2.dist-info/METADATA
docuwarp-1.0.2.dist-info/WHEEL
docuwarp-1.0.2.dist-info/entry_points.txt
docuwarp-1.0.2.dist-info/top_level.txt
docuwarp-1.0.2.dist-info/RECORD
