Metadata-Version: 2.1
Name: docuwarp
Version: 1.0.2
Summary: Unwarp documents
Home-page: https://github.com/pstwh/docuwarp
Keywords: document,unwarp,photo
Requires-Python: >=3.5, <4
Requires-Dist: pillow ==10.4.0
Provides-Extra: cpu
Requires-Dist: onnxruntime ==1.18.1 ; extra == 'cpu'
Provides-Extra: gpu
Requires-Dist: onnxruntime-gpu ==1.18.1 ; extra == 'gpu'
